microsoft_dynamics_auth.py
microsoft_dynamics_auth-1.0.0.dist-info/LICENSE
microsoft_dynamics_auth-1.0.0.dist-info/METADATA
microsoft_dynamics_auth-1.0.0.dist-info/WHEEL
microsoft_dynamics_auth-1.0.0.dist-info/entry_points.txt
microsoft_dynamics_auth-1.0.0.dist-info/top_level.txt
microsoft_dynamics_auth-1.0.0.dist-info/RECORD
