Metadata-Version: 2.1
Name: microsoft-dynamics-auth
Version: 1.0.0
Summary: Microsoft Power Platform authentication plugin for HTTPie.
Home-page: https://github.com/roshangautam/microsoft-dynamics-auth
Author: Roshan Gautam
Author-email: roshan.gautam@hotmail.com
License: MIT
Download-URL: https://github.com/roshangautam/microsoft-dynamics-auth
Platform: UNKNOWN
Classifier: Development Status :: 5 - Production/Stable
Classifier: Programming Language :: Python
Classifier: Intended Audience :: Developers
Classifier: Environment :: Plugins
Classifier: License :: OSI Approved :: MIT License
Classifier: Topic :: Internet :: WWW/HTTP
Classifier: Topic :: Utilities
Requires-Dist: httpie (>=0.9.9)
Requires-Dist: adal (>=1.1.0)
